fast_microservice/__about__.py
fast_microservice/__init__.py
fast_microservice/application.py
fast_microservice/helpers.py
fast_microservice/main.py
fast_microservice/py.typed
fast_microservice/routers/__init__.py
fast_microservice/routers/error.py
fast_microservice/routers/heartbeat.py
fast_microservice/routers/versions.py
fast_microservice/services/__init__.py
fast_microservice/settings/__init__.py
fast_microservice/settings/globals.py
fast_microservice-0.1.0rc4.dist-info/LICENSE
fast_microservice-0.1.0rc4.dist-info/WHEEL
fast_microservice-0.1.0rc4.dist-info/METADATA
fast_microservice-0.1.0rc4.dist-info/RECORD
