Metadata-Version: 2.1
Name: fast-microservice
Version: 0.1.0rc4
Summary: Small Microservice based on FastAPI
Home-page: https://github.com/jberends/fast-microservice
License: Apache 2.0
Author: Jochem Berends
Author-email: jberends@jbits.nl
Requires-Python: >=3.6.1,<4.0
Classifier: Development Status :: 2 - Pre-Alpha
Classifier: Environment :: Web Environment
Classifier: Intended Audience :: Developers
Classifier: License :: OSI Approved :: Apache Software License
Classifier: License :: Other/Proprietary License
Classifier: Operating System :: OS Independent
Classifier: Programming Language :: Python
Classifier: Programming Language :: Python :: 3
Classifier: Programming Language :: Python :: 3.6
Classifier: Programming Language :: Python :: 3.7
Classifier: Programming Language :: Python :: 3.8
Classifier: Programming Language :: Python :: 3.9
Classifier: Topic :: Internet :: WWW/HTTP
Classifier: Topic :: Software Development :: Libraries :: Python Modules
Classifier: Typing :: Typed
Requires-Dist: PyYAML (>=5.3.1,<6.0.0)
Requires-Dist: fastapi (>=0.63.0,<0.64.0)
Requires-Dist: pydantic (>=1.7.3,<2.0.0)
Requires-Dist: python-multipart (>=0.0.5,<0.0.6)
Requires-Dist: requests (>=2.25.1,<3.0.0)
Requires-Dist: requests-toolbelt (>=0.9.1,<0.10.0)
Requires-Dist: sentry-sdk (>=0.19.5,<0.20.0)
Requires-Dist: ujson (>=4.0.1,<5.0.0)
Requires-Dist: uvicorn (>=0.13.2,<0.14.0)
Project-URL: Documentation, https://github.com/jberends/fast-microservice/blob/master/README.md
Project-URL: Repository, https://github.com/jberends/fast-microservice
